README.md
setup.cfg
setup.py
pixaven/__init__.py
pixaven/client.py
pixaven.egg-info/PKG-INFO
pixaven.egg-info/SOURCES.txt
pixaven.egg-info/dependency_links.txt
pixaven.egg-info/requires.txt
pixaven.egg-info/top_level.txt